tapioca_gather/__init__.py
tapioca_gather/resource_mapping.py
tapioca_gather/tapioca_gather.py
tapioca_gather-0.0.3.dist-info/LICENSE
tapioca_gather-0.0.3.dist-info/METADATA
tapioca_gather-0.0.3.dist-info/WHEEL
tapioca_gather-0.0.3.dist-info/top_level.txt
tapioca_gather-0.0.3.dist-info/RECORD
