Metadata-Version: 2.1
Name: tapioca-gather
Version: 0.0.3
Summary: Gather API wrapper using tapioca
Home-page: https://github.com/pyanderson/tapioca-gather
Author: Anderson de Sousa Lima
Author-email: anderson.sl93@hotmail.com
License: MIT
Keywords: gather,gather-town,api,tapioca
Classifier: Development Status :: 5 - Production/Stable
Classifier: Intended Audience :: Developers
Classifier: License :: OSI Approved :: MIT License
Classifier: Natural Language :: English
Classifier: Programming Language :: Python :: 3
Classifier: Programming Language :: Python :: 3.1
Classifier: Programming Language :: Python :: 3.2
Classifier: Programming Language :: Python :: 3.3
Classifier: Programming Language :: Python :: 3.4
Classifier: Programming Language :: Python :: 3.5
Classifier: Programming Language :: Python :: 3.6
Classifier: Programming Language :: Python :: 3.7
Classifier: Programming Language :: Python :: 3.8
Classifier: Programming Language :: Python :: 3.9
License-File: LICENSE
Requires-Dist: tapioca-wrapper (==2.1.0)
